{"_id":"post-0449b9f3-8313-4726-81ca-cc271fc2eb73","_type":"post","title":"Require any npm package","slug":{"_type":"slug","current":"npm"},"body":[{"_key":"a44363bc4dd4","children":[{"_type":"span","marks":[],"text":"Last year we introduced support for importing ","_key":"a44363bc4dd40"},{"_type":"span","marks":["ac37e214100a"],"text":"any Python package from PyPi","_key":"a44363bc4dd41"},{"_type":"span","marks":[],"text":" and -- although we don't have perfect support for all packages -- it turned out to be a very popular feature. That's why today we're excited to continue the roll-out for the rest of our platform starting with web-based languages. [](preview end)","_key":"a44363bc4dd42"}],"markDefs":[{"_key":"ac37e214100a","_type":"link","href":"python-import"}],"_type":"block","style":"normal"},{"_key":"cfb8b5279d86","children":[{"_type":"span","marks":[],"text":"Whether you're using plain old ","_key":"cfb8b5279d860"},{"_type":"span","marks":["982755c2fc5a"],"text":"JavaScript REPL","_key":"cfb8b5279d861"},{"_type":"span","marks":[],"text":", ","_key":"cfb8b5279d862"},{"_type":"span","marks":["3b36604dd877"],"text":"HTML/CSS/JS","_key":"cfb8b5279d863"},{"_type":"span","marks":[],"text":", or ","_key":"cfb8b5279d864"},{"_type":"span","marks":["621a39878978"],"text":"ES2016","_key":"cfb8b5279d865"},{"_type":"span","marks":[],"text":", you'll be able to import any package from npm (that can run in the browser).","_key":"cfb8b5279d866"}],"markDefs":[{"_key":"982755c2fc5a","_type":"link","href":"/languages/javascript"},{"_key":"3b36604dd877","_type":"link","href":"/languages/html"},{"_key":"621a39878978","_type":"link","href":"/languages/babel"}],"_type":"block","style":"normal"},{"_key":"e955b947674e","children":[{"_type":"span","_key":"e955b947674e0","text":"","marks":[]}],"markDefs":[],"_type":"block","style":"normal"},{"_key":"0f30b07c5e32","children":[{"_type":"span","marks":[],"text":"How it works is that we parse out the requires from your code, fetch the bundle from npm via ","_key":"0f30b07c5e320"},{"_type":"span","marks":["ce8360b4d8b2"],"text":"wzrd.in","_key":"0f30b07c5e321"},{"_type":"span","marks":[],"text":", and evaluate the bundle in the same context as your code.","_key":"0f30b07c5e322"}],"markDefs":[{"_key":"ce8360b4d8b2","_type":"link","href":"https://wzrd.in"}],"_type":"block","style":"normal"},{"_key":"6180375f84b3","children":[{"_type":"span","marks":[],"text":"Note that ES6 imports is not currently supported but we're hoping to get it in soon.","_key":"6180375f84b30"}],"markDefs":[],"_type":"block","style":"normal"},{"_key":"7fa36670d457","children":[{"_type":"span","marks":[],"text":"Thanks to ","_key":"7fa36670d4570"},{"_type":"span","marks":["5976002834d4"],"text":"Phạm Ngọc Quang Nam","_key":"7fa36670d4571"},{"_type":"span","marks":[],"text":" for his work on this feature, npm for the registry, and wzrd.in for the awesome packaging service.","_key":"7fa36670d4572"}],"markDefs":[{"_key":"5976002834d4","_type":"link","href":"https://github.com/NamPNQ"}],"_type":"block","style":"normal"}],"publishedAt":"2017-03-28T07:00:00.000Z"}